{
  "$SysResult$" : {
    "$SysCode$" : 500,
    "$Content$" : {
      "SAUrl" : "http://cmbls/functionjump?id=123&action=gofuncid&funcid=0047063&clean=false&requesttype=post&cmb_app_trans_parms_start=here&XRIPINN=&XSAACOD=D07",
      "DisplayTrxType" : "银联在线支付",
      "GoodsName" : "",
      "SelfFlag" : "N",
      "TrxDes" : "银联在线支付，银联转账（云闪付）",
      "PRD_IN_CD" : "",
      "ChnCod" : "",
      "EncryEacId" : "3Y4vD4a8T6d02qW078+1e1fl9n35Tekhm03W/qMs+vo=",
      "OUT_PRD_NAM" : "",
      "CardNo" : "Tsd9+ERQZWdzXZ7YIyRXv5CqCYIFxav5t3DG0JKatYw=",
      "CurrencySymbol" : "￥",
      "TOT_FAV_AMT" : "",
      "DisplayRecieverBankNo" : "",
      "TrxCmt" : "",
      "RtFlag" : "B",
      "HaveUid" : "Y",
      "CreditTrxCode" : "",
      "TransNo" : "PGT6FS09015CMTT002000",
      "ChangeFlag" : "Y",
      "IN_PRD_NAM" : "",
      "DatMon" : "202211",
      "DisplayNo" : "一卡通 6214********8168",
      "DESUnShow" : "%e9%93%b6%e8%81%94%e8%bd%ac%e8%b4%a6%ef%bc%88%e4%ba%91%e9%97%aa%e4%bb%98%ef%bc%89",
      "TRS_CMT" : "",
      "CcyCode" : "10",
      "MerchanrName" : "银联在线支付，银联转账（云闪付）",
      "EnterAcountFlag" : "N",
      "TrxFlag" : "B",
      "IsCare" : "N",
      "TrxTxt" : "",
      "ConductUrl" : "http://cmbls/functionjump?id=123&action=gofuncid&funcid=6016005&clean=false&requesttype=post&cmb_app_trans_parms_start=here&Code=",
      "BookNameShow" : "请选择",
      "EnterDate" : "1900-01-01",
      "TrxLevel1" : "11",
      "TrxTime" : "2022-11-09 10:03:45",
      "PRD_CD" : "",
      "CountryName" : "",
      "ORD_REF_NBR" : "",
      "OriTrxAmount" : "-94,064.29",
      "TrxLevel2" : "1117",
      "TrxDesDataFlag" : "0",
      "OriTrxCurrcency" : "10",
      "TrxLevel3" : "A",
      "DisplayCardType" : "一卡通",
      "DisplayCardNo4" : "8168",
      "IllegalNum" : 0,
      "DisplayCurrency" : "",
      "TrxAmount" : "￥94,064.29",
      "DisplayRecieverName" : "",
      "ORG_ORD_AMT" : "",
      "TrxCode" : "CUNP",
      "DiaplayPayName" : "",
      "AgentCompany" : "",
      "AgentCompanyDel" : "",
      "DetailType" : "04",
      "BookNameShowCheck" : "N",
      "CardType" : "A",
      "DB1Code" : "108",
      "ImmersiveVersion" : "4.4.0",
      "DisplayPayBankNo" : "",
      "ForeignFlag" : "0",
      "FundUrl" : "http://cmbls/functionjump?action=gofuncid&funcid=0055008&clean=false&requesttype=post&cmb_app_trans_parms_start=here&FundCode=",
      "DisplayAmount" : "人民币10",
      "ErrCode" : "EmptyData",
      "SCE_SRC" : "",
      "BalanceAmount" : "68,677.20",
      "ChnNam" : "无",
      "VoiceAmout" : "人民币94,064.29",
      "TRX_AMTORG" : "-94064.29",
      "UserDes" : "",
      "CityCode" : "",
      "DatDte" : "2022-11-09",
      "DisplayOriTrxCurrcency" : "人民币(￥)",
      "OriTrxCurrcencysymbol" : "￥",
      "PRD_NM" : "",
      "RmbAmt" : "94064.29",
      "CountryCode" : ""
    }
  }
}
